{"type":"FeatureCollection","features":[{"type": "Feature", "properties": {"OBJECTID": 145181, "MONUID": "MYO1076", "RECORDTYPE": "BLD", "NAME": "OBSERVATORY", "MONTYPE": "OBSERVATORY", "GATEWAYURL": "http://www.heritagegateway.org.uk/Gateway/Results_Single.aspx?resourceID=1003&uid=MYO1076"}, "geometry": {"type": "Point", "coordinates": [-1.0880056206670377, 53.96121475639997]}},{"type": "Feature", "properties": {"OBJECTID": 145182, "MONUID": "MYO1077", "RECORDTYPE": "BLD", "NAME": "RAILINGS AND GATES FORMING SOUTH WEST BOUNDARY OF MUSEUM GARDENS", "MONTYPE": "BOUNDARY WALL, GATE, GATE PIER, RAILINGS", "GATEWAYURL": "http://www.heritagegateway.org.uk/Gateway/Results_Single.aspx?resourceID=1003&uid=MYO1077"}, "geometry": {"type": "Point", "coordinates": [-1.0904927187942772, 53.96108979830314]}},{"type": "Feature", "properties": {"OBJECTID": 145763, "MONUID": "MYO2279", "RECORDTYPE": "BLD", "NAME": "Scarborough Bridge", "MONTYPE": "RAILWAY BRIDGE", "GATEWAYURL": "http://www.heritagegateway.org.uk/Gateway/Results_Single.aspx?resourceID=1003&uid=MYO2279"}, "geometry": {"type": "Point", "coordinates": [-1.092832043727887, 53.961206792512584]}},{"type": "Feature", "properties": {"OBJECTID": 147516, "MONUID": "MYO3759", "RECORDTYPE": "MON", "NAME": "Water Tower & Pumping Station (1877, to pump water up from river).", "MONTYPE": "HOUSING ESTATE", "GATEWAYURL": "http://www.heritagegateway.org.uk/Gateway/Results_Single.aspx?resourceID=1003&uid=MYO3759"}, "geometry": {"type": "Point", "coordinates": [-1.0934132694540353, 53.96067103073278]}}]}